onnx_card/__init__.py
onnx_card/__main__.py
onnx_card/cli.py
onnx_card/core.py
onnx_card/render.py
onnx_card/types.py
onnx_card-0.1.0.dist-info/METADATA
onnx_card-0.1.0.dist-info/WHEEL
onnx_card-0.1.0.dist-info/entry_points.txt
onnx_card-0.1.0.dist-info/licenses/LICENSE
onnx_card-0.1.0.dist-info/RECORD
