Metadata-Version: 2.4
Name: onnx-card
Version: 0.1.0
Summary: Fast, accurate, terminal-first ONNX model cards — describe what's inside an ONNX model without running it.
Project-URL: Homepage, https://github.com/boijuny/onnx-card
Project-URL: Repository, https://github.com/boijuny/onnx-card
Project-URL: Issues, https://github.com/boijuny/onnx-card/issues
Author: Matthieu Marchal
License: MIT License
License-File: LICENSE
Keywords: cli,machine-learning,model-inspection,onnx,terminal
Classifier: Development Status :: 3 - Alpha
Classifier: Intended Audience :: Developers
Classifier: Intended Audience :: Science/Research
Classifier: License :: OSI Approved :: MIT License
Classifier: Programming Language :: Python :: 3
Classifier: Programming Language :: Python :: 3.9
Classifier: Programming Language :: Python :: 3.10
Classifier: Programming Language :: Python :: 3.11
Classifier: Programming Language :: Python :: 3.12
Classifier: Topic :: Scientific/Engineering :: Artificial Intelligence
Classifier: Topic :: Software Development :: Libraries :: Python Modules
Requires-Python: >=3.9
Requires-Dist: onnx>=1.14
Requires-Dist: rich>=13
